jso/__init__.py
jso/misc.so
jso/misc_py.py
jso-1.0.5.dist-info/licenses/LICENSE
jso-1.0.5.dist-info/METADATA
jso-1.0.5.dist-info/WHEEL
jso-1.0.5.dist-info/top_level.txt
jso-1.0.5.dist-info/RECORD
