Metadata-Version: 2.4
Name: jso
Version: 1.0.5
Author: thorraythorray
Author-email: jso@live.com
Classifier: Programming Language :: Python :: 3
Classifier: License :: OSI Approved :: MIT License
Classifier: Operating System :: OS Independent
Requires-Python: >=3
License-File: LICENSE
Requires-Dist: pynetdicom
Requires-Dist: pydicom
Requires-Dist: cx_Oracle
Dynamic: author
Dynamic: author-email
Dynamic: classifier
Dynamic: description-content-type
Dynamic: license-file
Dynamic: requires-dist
Dynamic: requires-python
